[
 {
  "keywords": [
   [
    "bomb", 
    3, 
    0.04929577464788732
   ], 
   [
    "threat", 
    3, 
    0.04929577464788732
   ], 
   [
    "entrargli", 
    3, 
    0.04929577464788732
   ], 
   [
    "january", 
    0, 
    0.04225352112676056
   ], 
   [
    "jan", 
    0, 
    0.04225352112676056
   ], 
   [
    "black", 
    3, 
    0.04225352112676056
   ], 
   [
    "breakfast", 
    3, 
    0.04225352112676056
   ], 
   [
    "executive", 
    3, 
    0.035211267605633804
   ], 
   [
    "salo", 
    3, 
    0.035211267605633804
   ], 
   [
    "maha", 
    3, 
    0.035211267605633804
   ], 
   [
    "sedan", 
    3, 
    0.035211267605633804
   ], 
   [
    "caterers", 
    3, 
    0.035211267605633804
   ], 
   [
    "health", 
    3, 
    0.02112676056338028
   ], 
   [
    "gastech", 
    1, 
    0.014084507042253521
   ], 
   [
    "pok", 
    2, 
    0.014084507042253521
   ], 
   [
    "site", 
    3, 
    0.014084507042253521
   ], 
   [
    "announces", 
    3, 
    0.014084507042253521
   ], 
   [
    "hardly", 
    3, 
    0.014084507042253521
   ], 
   [
    "elodis", 
    1, 
    0.014084507042253521
   ], 
   [
    "incidents", 
    3, 
    0.014084507042253521
   ]
  ], 
  "TopicNum: ": 0
 }, 
 {
  "keywords": [
   [
    "edvard", 
    2, 
    0.038910505836575876
   ], 
   [
    "kronos", 
    1, 
    0.03501945525291829
   ], 
   [
    "fire", 
    3, 
    0.0311284046692607
   ], 
   [
    "gastech", 
    1, 
    0.027237354085603113
   ], 
   [
    "alarm", 
    3, 
    0.023346303501945526
   ], 
   [
    "offer", 
    3, 
    0.019455252918287938
   ], 
   [
    "tethan", 
    1, 
    0.019455252918287938
   ], 
   [
    "local", 
    3, 
    0.01556420233463035
   ], 
   [
    "help", 
    3, 
    0.01556420233463035
   ], 
   [
    "clean", 
    3, 
    0.01556420233463035
   ], 
   [
    "protesters", 
    3, 
    0.01556420233463035
   ], 
   [
    "pok", 
    2, 
    0.011673151750972763
   ], 
   [
    "ministers", 
    3, 
    0.011673151750972763
   ], 
   [
    "company", 
    3, 
    0.011673151750972763
   ], 
   [
    "missing", 
    3, 
    0.011673151750972763
   ], 
   [
    "police", 
    3, 
    0.011673151750972763
   ], 
   [
    "blue", 
    3, 
    0.011673151750972763
   ], 
   [
    "force", 
    3, 
    0.011673151750972763
   ], 
   [
    "flame", 
    3, 
    0.011673151750972763
   ], 
   [
    "suffer", 
    3, 
    0.011673151750972763
   ]
  ], 
  "TopicNum: ": 1
 }, 
 {
  "keywords": [
   [
    "kronos", 
    1, 
    0.052083333333333336
   ], 
   [
    "guard", 
    3, 
    0.046875
   ], 
   [
    "contamination", 
    3, 
    0.046875
   ], 
   [
    "gastech", 
    1, 
    0.041666666666666664
   ], 
   [
    "pok", 
    2, 
    0.041666666666666664
   ], 
   [
    "groups", 
    3, 
    0.020833333333333332
   ], 
   [
    "president", 
    2, 
    0.020833333333333332
   ], 
   [
    "responsibility", 
    3, 
    0.020833333333333332
   ], 
   [
    "international", 
    3, 
    0.020833333333333332
   ], 
   [
    "several", 
    3, 
    0.020833333333333332
   ], 
   [
    "death", 
    3, 
    0.020833333333333332
   ], 
   [
    "year", 
    3, 
    0.020833333333333332
   ], 
   [
    "water", 
    3, 
    0.020833333333333332
   ], 
   [
    "polluted", 
    3, 
    0.020833333333333332
   ], 
   [
    "sickness", 
    3, 
    0.020833333333333332
   ], 
   [
    "tethys", 
    1, 
    0.015625
   ], 
   [
    "riot", 
    3, 
    0.015625
   ], 
   [
    "questions", 
    3, 
    0.010416666666666666
   ], 
   [
    "sten", 
    2, 
    0.010416666666666666
   ], 
   [
    "organizations", 
    3, 
    0.010416666666666666
   ]
  ], 
  "TopicNum: ": 2
 }
]