[
 {
  "keywords": [
   [
    "gastech", 
    1, 
    0.05434782608695652
   ], 
   [
    "contamination", 
    3, 
    0.04891304347826087
   ], 
   [
    "year", 
    3, 
    0.02717391304347826
   ], 
   [
    "water", 
    3, 
    0.02717391304347826
   ], 
   [
    "groups", 
    3, 
    0.021739130434782608
   ], 
   [
    "kronos", 
    1, 
    0.021739130434782608
   ], 
   [
    "president", 
    2, 
    0.021739130434782608
   ], 
   [
    "international", 
    3, 
    0.021739130434782608
   ], 
   [
    "elodis", 
    1, 
    0.021739130434782608
   ], 
   [
    "polluted", 
    3, 
    0.021739130434782608
   ], 
   [
    "sickness", 
    3, 
    0.021739130434782608
   ], 
   [
    "pok", 
    2, 
    0.016304347826086956
   ], 
   [
    "health", 
    3, 
    0.016304347826086956
   ], 
   [
    "supplies", 
    3, 
    0.016304347826086956
   ], 
   [
    "sten", 
    2, 
    0.010869565217391304
   ], 
   [
    "organizations", 
    3, 
    0.010869565217391304
   ], 
   [
    "responsibility", 
    3, 
    0.010869565217391304
   ], 
   [
    "subsequently", 
    3, 
    0.010869565217391304
   ], 
   [
    "local", 
    3, 
    0.010869565217391304
   ], 
   [
    "sanjorge", 
    2, 
    0.010869565217391304
   ]
  ], 
  "TopicNum: ": 0
 }, 
 {
  "keywords": [
   [
    "executive", 
    3, 
    0.16666666666666666
   ], 
   [
    "breakfast", 
    3, 
    0.16666666666666666
   ], 
   [
    "caterers", 
    3, 
    0.125
   ], 
   [
    "plane", 
    3, 
    0.1
   ], 
   [
    "drug", 
    3, 
    0.1
   ], 
   [
    "new", 
    3, 
    0.1
   ], 
   [
    "increased", 
    3, 
    0.1
   ], 
   [
    "private", 
    3, 
    0.1
   ], 
   [
    "pok", 
    2, 
    0.08333333333333333
   ], 
   [
    "groups", 
    3, 
    0.041666666666666664
   ], 
   [
    "kronos", 
    1, 
    0.041666666666666664
   ], 
   [
    "responsibility", 
    3, 
    0.041666666666666664
   ], 
   [
    "support", 
    3, 
    0.041666666666666664
   ], 
   [
    "concerns", 
    3, 
    0.041666666666666664
   ], 
   [
    "denied", 
    3, 
    0.041666666666666664
   ], 
   [
    "attacks", 
    3, 
    0.041666666666666664
   ], 
   [
    "accuse", 
    3, 
    0.041666666666666664
   ], 
   [
    "frame", 
    3, 
    0.041666666666666664
   ], 
   [
    "silence", 
    3, 
    0.041666666666666664
   ], 
   [
    "staging", 
    3, 
    0.041666666666666664
   ]
  ], 
  "TopicNum: ": 1
 }, 
 {
  "keywords": [
   [
    "tethan", 
    1, 
    0.2
   ], 
   [
    "explosion", 
    3, 
    0.1
   ], 
   [
    "tiskele", 
    3, 
    0.1
   ], 
   [
    "bend", 
    3, 
    0.1
   ], 
   [
    "city", 
    3, 
    0.1
   ], 
   [
    "centrum", 
    3, 
    0.1
   ], 
   [
    "gas", 
    3, 
    0.1
   ], 
   [
    "opening", 
    3, 
    0.1
   ], 
   [
    "police", 
    3, 
    0.06666666666666667
   ], 
   [
    "fire", 
    3, 
    0.06666666666666667
   ], 
   [
    "citizens", 
    3, 
    0.06666666666666667
   ], 
   [
    "force", 
    3, 
    0.06666666666666667
   ], 
   [
    "violent", 
    3, 
    0.06666666666666667
   ], 
   [
    "protesters", 
    3, 
    0.06666666666666667
   ], 
   [
    "fatal", 
    3, 
    0.06666666666666667
   ], 
   [
    "sometimes", 
    3, 
    0.06666666666666667
   ], 
   [
    "caught", 
    3, 
    0.06666666666666667
   ], 
   [
    "cross", 
    3, 
    0.06666666666666667
   ], 
   [
    "peaceful", 
    3, 
    0.06666666666666667
   ], 
   [
    "nitially", 
    3, 
    0.06666666666666667
   ]
  ], 
  "TopicNum: ": 2
 }, 
 {
  "keywords": [
   [
    "guard", 
    3, 
    0.041916167664670656
   ], 
   [
    "kronos", 
    1, 
    0.03592814371257485
   ], 
   [
    "gastech", 
    1, 
    0.023952095808383235
   ], 
   [
    "clean", 
    3, 
    0.023952095808383235
   ], 
   [
    "pok", 
    2, 
    0.017964071856287425
   ], 
   [
    "company", 
    3, 
    0.017964071856287425
   ], 
   [
    "businesses", 
    3, 
    0.017964071856287425
   ], 
   [
    "transparency", 
    3, 
    0.017964071856287425
   ], 
   [
    "blue", 
    3, 
    0.017964071856287425
   ], 
   [
    "karel", 
    2, 
    0.017964071856287425
   ], 
   [
    "hold", 
    3, 
    0.017964071856287425
   ], 
   [
    "flame", 
    3, 
    0.017964071856287425
   ], 
   [
    "protesters", 
    3, 
    0.017964071856287425
   ], 
   [
    "suffer", 
    3, 
    0.017964071856287425
   ], 
   [
    "questions", 
    3, 
    0.011976047904191617
   ], 
   [
    "initial", 
    3, 
    0.011976047904191617
   ], 
   [
    "responsibility", 
    3, 
    0.011976047904191617
   ], 
   [
    "members", 
    3, 
    0.011976047904191617
   ], 
   [
    "offer", 
    3, 
    0.011976047904191617
   ], 
   [
    "hour", 
    3, 
    0.011976047904191617
   ]
  ], 
  "TopicNum: ": 3
 }, 
 {
  "keywords": [
   [
    "pok", 
    2, 
    0.1111111111111111
   ], 
   [
    "ministers", 
    3, 
    0.1111111111111111
   ], 
   [
    "riot", 
    3, 
    0.1111111111111111
   ], 
   [
    "annual", 
    3, 
    0.1
   ], 
   [
    "oil", 
    3, 
    0.1
   ], 
   [
    "siopa", 
    3, 
    0.1
   ], 
   [
    "district", 
    3, 
    0.1
   ], 
   [
    "vandalize", 
    3, 
    0.1
   ], 
   [
    "crowd", 
    3, 
    0.1
   ], 
   [
    "employs", 
    3, 
    0.1
   ], 
   [
    "black", 
    3, 
    0.1
   ], 
   [
    "kronos", 
    1, 
    0.07407407407407407
   ], 
   [
    "affairs", 
    3, 
    0.07407407407407407
   ], 
   [
    "tethan", 
    1, 
    0.07407407407407407
   ], 
   [
    "police", 
    3, 
    0.07407407407407407
   ], 
   [
    "ministry", 
    3, 
    0.07407407407407407
   ], 
   [
    "foreign", 
    3, 
    0.07407407407407407
   ], 
   [
    "help", 
    3, 
    0.07407407407407407
   ], 
   [
    "force", 
    3, 
    0.07407407407407407
   ], 
   [
    "personnel", 
    3, 
    0.07407407407407407
   ]
  ], 
  "TopicNum: ": 4
 }, 
 {
  "keywords": [
   [
    "edvard", 
    2, 
    0.05747126436781609
   ], 
   [
    "kronos", 
    1, 
    0.040229885057471264
   ], 
   [
    "fire", 
    3, 
    0.040229885057471264
   ], 
   [
    "bomb", 
    3, 
    0.040229885057471264
   ], 
   [
    "threat", 
    3, 
    0.040229885057471264
   ], 
   [
    "entrargli", 
    3, 
    0.040229885057471264
   ], 
   [
    "january", 
    0, 
    0.034482758620689655
   ], 
   [
    "alarm", 
    3, 
    0.034482758620689655
   ], 
   [
    "jan", 
    0, 
    0.034482758620689655
   ], 
   [
    "black", 
    3, 
    0.034482758620689655
   ], 
   [
    "salo", 
    3, 
    0.028735632183908046
   ], 
   [
    "maha", 
    3, 
    0.028735632183908046
   ], 
   [
    "sedan", 
    3, 
    0.028735632183908046
   ], 
   [
    "local", 
    3, 
    0.022988505747126436
   ], 
   [
    "gastech", 
    1, 
    0.017241379310344827
   ], 
   [
    "offer", 
    3, 
    0.017241379310344827
   ], 
   [
    "morning", 
    3, 
    0.011494252873563218
   ], 
   [
    "event", 
    3, 
    0.011494252873563218
   ], 
   [
    "organizations", 
    3, 
    0.011494252873563218
   ], 
   [
    "pok", 
    2, 
    0.011494252873563218
   ]
  ], 
  "TopicNum: ": 5
 }
]