[
 {
  "keywords": [
   "share", 
   "stock", 
   "market", 
   "compani", 
   "cent", 
   "million", 
   "price", 
   "bomb", 
   "year", 
   "fell", 
   "index", 
   "new", 
   "trade", 
   "sale", 
   "rose"
  ], 
  "TopicNum: ": 0
 }, 
 {
  "keywords": [
   "democrat", 
   "parti", 
   "pain", 
   "women", 
   "abort", 
   ".''", 
   "vastopoli", 
   "convent", 
   "saudi", 
   "charact", 
   "issu", 
   "life", 
   "gun", 
   "derryberri", 
   "american"
  ], 
  "TopicNum: ": 1
 }, 
 {
  "keywords": [
   "fund", 
   "year", 
   "compani", 
   "manag", 
   "market", 
   "invest", 
   "new", 
   ".''", 
   "secur", 
   "tax", 
   "also", 
   "rate", 
   "million", 
   "stock", 
   "may"
  ], 
  "TopicNum: ": 2
 }, 
 {
  "keywords": [
   "game", 
   ".''", 
   "codi", 
   "missil", 
   "atlanta", 
   "parti", 
   "year", 
   "secur", 
   "presid", 
   "bankruptci", 
   "offici", 
   "peopl", 
   "citi", 
   "day", 
   "take"
  ], 
  "TopicNum: ": 3
 }, 
 {
  "keywords": [
   "year", 
   "lloyd", 
   "million", 
   ".''", 
   "compani", 
   "presid", 
   "new", 
   "insur", 
   "market", 
   "plan", 
   "name", 
   "make", 
   "team", 
   "may", 
   "billion"
  ], 
  "TopicNum: ": 4
 }
]